{
  "namespaces": [],
  "tables": [
    {
      "columns": {
        "id": {
          "name": "id",
          "type": "integer",
          "unsigned": true,
          "autoincrement": true,
          "primary": true,
          "nullable": false,
          "mappedType": "integer"
        },
        "name": {
          "name": "name",
          "type": "text",
          "unsigned": false,
          "autoincrement": false,
          "primary": false,
          "nullable": false,
          "mappedType": "text"
        }
      },
      "name": "robots",
      "indexes": [
        {
          "keyName": "primary",
          "columnNames": [
            "id"
          ],
          "composite": false,
          "primary": true,
          "unique": true
        }
      ],
      "checks": [],
      "foreignKeys": {}
    },
    {
      "columns": {
        "id": {
          "name": "id",
          "type": "integer",
          "unsigned": true,
          "autoincrement": true,
          "primary": true,
          "nullable": false,
          "mappedType": "integer"
        },
        "robot_id": {
          "name": "robot_id",
          "type": "integer",
          "unsigned": false,
          "autoincrement": false,
          "primary": false,
          "nullable": false,
          "mappedType": "integer"
        },
        "name": {
          "name": "name",
          "type": "text",
          "unsigned": false,
          "autoincrement": false,
          "primary": false,
          "nullable": false,
          "mappedType": "text"
        },
        "priority": {
          "name": "priority",
          "type": "text",
          "unsigned": false,
          "autoincrement": false,
          "primary": false,
          "nullable": false,
          "default": "'LOW'",
          "enumItems": [
            "HIGH",
            "MEDIUM",
            "LOW"
          ],
          "mappedType": "enum"
        },
        "task_time_seconds": {
          "name": "task_time_seconds",
          "type": "integer",
          "unsigned": false,
          "autoincrement": false,
          "primary": false,
          "nullable": false,
          "mappedType": "integer"
        },
        "status": {
          "name": "status",
          "type": "text",
          "unsigned": false,
          "autoincrement": false,
          "primary": false,
          "nullable": false,
          "enumItems": [
            "QUEUED",
            "ACTIVE",
            "COMPLETED",
            "ABANDONED"
          ],
          "mappedType": "enum"
        },
        "created_at": {
          "name": "created_at",
          "type": "datetime",
          "unsigned": false,
          "autoincrement": false,
          "primary": false,
          "nullable": false,
          "length": 0,
          "mappedType": "datetime"
        },
        "updated_at": {
          "name": "updated_at",
          "type": "datetime",
          "unsigned": false,
          "autoincrement": false,
          "primary": false,
          "nullable": false,
          "length": 0,
          "mappedType": "datetime"
        },
        "updated_by": {
          "name": "updated_by",
          "type": "text",
          "unsigned": false,
          "autoincrement": false,
          "primary": false,
          "nullable": false,
          "mappedType": "text"
        }
      },
      "name": "tasks",
      "indexes": [
        {
          "columnNames": [
            "robot_id"
          ],
          "composite": false,
          "keyName": "tasks_robot_id_index",
          "primary": false,
          "unique": false
        },
        {
          "keyName": "primary",
          "columnNames": [
            "id"
          ],
          "composite": false,
          "primary": true,
          "unique": true
        }
      ],
      "checks": [],
      "foreignKeys": {
        "tasks_robot_id_foreign": {
          "constraintName": "tasks_robot_id_foreign",
          "columnNames": [
            "robot_id"
          ],
          "localTableName": "tasks",
          "referencedColumnNames": [
            "id"
          ],
          "referencedTableName": "robots",
          "updateRule": "cascade"
        }
      }
    }
  ]
}
